PTLF/__init__.py
PTLF/_pipeline.py
PTLF/_version.py
PTLF/context.py
PTLF/experiment.py
PTLF/lab.py
PTLF/utils.py
pytorchlabflow-0.4.7.1.dist-info/licenses/LICENSE
pytorchlabflow-0.4.7.1.dist-info/METADATA
pytorchlabflow-0.4.7.1.dist-info/WHEEL
pytorchlabflow-0.4.7.1.dist-info/top_level.txt
pytorchlabflow-0.4.7.1.dist-info/RECORD
