Metadata-Version: 2.4
Name: PyTorchLabFlow
Version: 0.4.7.1
Summary: PyTorchLabFlow is a lightweight framework that simplifies PyTorch experiment management...
Home-page: https://github.com/BBEK-Anand/PyTorchLabFlow
Author: BBEK-Anand
Author-email: 
License: Apache-2.0
Classifier: Programming Language :: Python :: 3
Classifier: License :: OSI Approved :: Apache Software License
Classifier: Operating System :: OS Independent
Requires-Python: >=3.7
License-File: LICENSE
Requires-Dist: torch
Requires-Dist: matplotlib
Requires-Dist: pandas
Requires-Dist: tqdm
Dynamic: author
Dynamic: classifier
Dynamic: description
Dynamic: description-content-type
Dynamic: home-page
Dynamic: license
Dynamic: license-file
Dynamic: requires-dist
Dynamic: requires-python
Dynamic: summary
